id_phonenumbers/__init__.py
id_phonenumbers/data.py
id_phonenumbers/number.py
id_phonenumbers-0.4.0.dist-info/LICENSE.txt
id_phonenumbers-0.4.0.dist-info/METADATA
id_phonenumbers-0.4.0.dist-info/WHEEL
id_phonenumbers-0.4.0.dist-info/top_level.txt
id_phonenumbers-0.4.0.dist-info/RECORD
