Metadata-Version: 2.1
Name: id-phonenumbers
Version: 0.4.0
Summary: Indonesian Phonenumbers Parser
Home-page: https://github.com/SeiryuZ/id_phonenumbers
Author: Steven
Author-email: stvn.bu@gmail.com
License: MIT
Download-URL: https://github.com/SeiryuZ/id_phonenumbers/tarball/0.2.0
Keywords: phonenumbers,Indonesia
Platform: UNKNOWN
Classifier: Development Status :: 3 - Alpha
Classifier: Intended Audience :: Developers
Classifier: Programming Language :: Python
Classifier: Programming Language :: Python :: 2
Classifier: Programming Language :: Python :: 2.7
Classifier: Programming Language :: Python :: 3
Classifier: Programming Language :: Python :: 3.3
Classifier: Programming Language :: Python :: 3.4
Classifier: Programming Language :: Python :: 3.5
Classifier: Programming Language :: Python :: 3.6
Classifier: License :: OSI Approved :: MIT License
Classifier: Operating System :: OS Independent
Classifier: Topic :: Internet :: WWW/HTTP
Classifier: Topic :: Software Development :: Libraries :: Python Modules
Requires-Dist: phonenumberslite
